Asyn_Fifo/DUT/fifo_mem.sv
`timescale 1ns/1ps
module fifo_mem #(
    parameter ADDR_SIZE = 4,
    parameter DATA_SIZE = 8
) (
    output logic [DATA_SIZE-1 : 0] r_data,
    input [ADDR_SIZE-1 : 0] r_addr,
    input [DATA_SIZE-1 : 0] w_data,
    input w_en,
    input w_clk,
    input w_full,
    input [ADDR_SIZE-1 : 0] w_addr
);

    localparam DEPTH = 1 << ADDR_SIZE;
    logic [DATA_SIZE-1 : 0] fifo_data [0 : DEPTH-1];

    //always @(posedge w_clk) begin
    always @(*) begin
        if(w_en && !w_full) begin
            fifo_data[w_addr] = w_data;
        end
    end

    always @(*) begin
        r_data = fifo_data[r_addr];
    end

endmodule

Asyn_Fifo/DUT/full_checker.sv
`timescale 1ns/1ps
module full_checker #(
    ADDR_SIZE = 4
) (
    w_en,
    w_clk,
    w_rst,
    w_full,
    w_addr,
    w_ptr_gray,
    r_ptr_gray
);

input [ADDR_SIZE : 0] r_ptr_gray; // from sync from empty
input w_clk;
input w_rst;
input w_en;

output logic [ADDR_SIZE-1 : 0] w_addr;
output logic w_full;
output logic [ADDR_SIZE : 0] w_ptr_gray; // to sync to empty

logic [ADDR_SIZE : 0]   w_ptr_gray_next;
logic [ADDR_SIZE : 0]   r_ptr_gray_next;
logic                   w_full_tmp;
//logic [ADDR_SIZE-1 : 0] w_addr_tmp;
logic [ADDR_SIZE : 0]   w_ptr_bin;
logic [ADDR_SIZE : 0]   w_ptr_bin_next;


always @(posedge w_clk or negedge w_rst) begin
    if(!w_rst) begin
        // w_addr     <= 0;
        w_ptr_gray <= 0;
        w_full     <= 0;
        w_ptr_bin  <= 0;
    end
    else begin
        // w_addr      <= w_addr_tmp;
        w_ptr_gray  <= w_ptr_gray_next;
        w_full      <= w_full_tmp;
        w_ptr_bin   <= w_ptr_bin_next;
    end
end

always @* begin
    // w_addr_tmp = w_ptr_bin[ADDR_SIZE-1 : 0]; // current address
    w_addr = w_ptr_bin[ADDR_SIZE-1 : 0];
    w_ptr_bin_next = w_ptr_bin + ({4'b0000, !w_full} & {4'b0000, w_en}); // move the w_ptr
    w_ptr_gray_next = w_ptr_bin_next ^ (w_ptr_bin_next >> 1); //convert to gray code
    r_ptr_gray_next = {~r_ptr_gray[ADDR_SIZE : ADDR_SIZE-1], r_ptr_gray[ADDR_SIZE-2 : 0]};
    if(w_ptr_gray_next == r_ptr_gray_next) begin
        w_full_tmp = 1;
    end
    else begin
        w_full_tmp = 0;
    end
end

endmodule

Asyn_Fifo/DUT/empty_checker.sv
`timescale 1ns/1ps

module empty_checker #(
    parameter ADDR_SIZE = 4
) (
    r_empty,
    r_ptr_gray,
    r_addr,
    w_ptr_gray,
    r_en,
    r_clk,
    r_rst
);

    output logic                   r_empty;
    output logic [ADDR_SIZE : 0]   r_ptr_gray;
    output logic [ADDR_SIZE-1 : 0] r_addr;

    input  [ADDR_SIZE : 0]   w_ptr_gray;
    input                    r_en;
    input                    r_clk;
    input                    r_rst;

    logic [ADDR_SIZE : 0]   r_ptr_gray_next;
    logic [ADDR_SIZE : 0]   r_ptr_bin;
    logic [ADDR_SIZE : 0]   r_ptr_bin_next;
    // logic [ADDR_SIZE-1 : 0] r_addr_tmp;
    logic                   r_empty_tmp;

    always @(posedge r_clk or negedge r_rst) begin
        if(!r_rst) begin
            r_empty    <= 1;
            r_ptr_gray <= 0;
            // r_addr     <= 0;
            r_ptr_bin  <= 0;
        end
        else begin
            r_empty     <= r_empty_tmp;
            r_ptr_gray  <= r_ptr_gray_next;
            // r_addr      <= r_addr_tmp;
            r_ptr_bin   <= r_ptr_bin_next;
        end
    end

    always @(*) begin

        // r_addr_tmp = r_ptr_bin[ADDR_SIZE-1 : 0];
        r_addr = r_ptr_bin[ADDR_SIZE-1 : 0];
        r_ptr_bin_next = r_ptr_bin + ({4'b0000, !r_empty} & {4'b0000, r_en});
        r_ptr_gray_next = r_ptr_bin_next ^ (r_ptr_bin_next >> 1);

        if(r_ptr_gray_next == w_ptr_gray) begin
            r_empty_tmp = 1;
        end
        else begin
            r_empty_tmp = 0;
        end
    end

endmodule

Asyn_Fifo/DUT/sync_2ff.sv
`timescale 1ns/1ps
module sync_2ff #(
    parameter ADDR_SIZE = 4
) (
    o_ptr,
    i_ptr,
    clk,
    rst
);
    input  [ADDR_SIZE : 0] i_ptr;
    output logic [ADDR_SIZE : 0] o_ptr;
    input clk;
    input rst;

    logic [ADDR_SIZE : 0] ptr_temp;

    always @(posedge clk or negedge rst) begin
        if(rst != 1) begin
            ptr_temp <= 0;
            o_ptr <= 0;
        end else begin
            ptr_temp <= i_ptr;
            o_ptr <= ptr_temp;
        end
    end
endmodule

Asyn_Fifo/DUT/async_fifo.sv
`timescale 1ns/1ps

module async_fifo #(
    parameter DATA_SIZE = 8,
    parameter ADDR_SIZE  = 4
) (
    w_full, 
    w_data,
    w_en,
    w_clk,
    w_rst,

    r_en,
    r_clk,
    r_rst,
    r_data,
    r_empty
);

    output logic [DATA_SIZE-1 : 0] r_data;
    output logic                  w_full;
    output logic                  r_empty;

    input [DATA_SIZE-1 : 0]  w_data;
    input                    w_en;
    input                    w_rst;
    input                    w_clk;
    input                    r_en;
    input                    r_clk;
    input                    r_rst;

    logic [ADDR_SIZE-1 : 0]   w_addr;
    logic [ADDR_SIZE-1 : 0]   r_addr;
    logic [ADDR_SIZE : 0]     w_ptr_i;
    logic [ADDR_SIZE : 0]     r_ptr_i;
    logic [ADDR_SIZE : 0]     w_ptr_o;
    logic [ADDR_SIZE : 0]     r_ptr_o;

    sync_2ff #(ADDR_SIZE) r_sync (
        .i_ptr(r_ptr_i),
        .o_ptr(r_ptr_o),
        .clk(r_clk),
        .rst(r_rst)
    );

    sync_2ff #(ADDR_SIZE) w_sync (
        .i_ptr(w_ptr_i),
        .o_ptr(w_ptr_o),
        .clk(w_clk),
        .rst(w_rst)
    );
    
    empty_checker #(ADDR_SIZE) r_empty_checker (
        .r_clk(r_clk),
        .r_en(r_en),
        .r_rst(r_rst),
        .r_addr(r_addr),
        .r_ptr_gray(r_ptr_i),
        .w_ptr_gray(w_ptr_o),
        .r_empty(r_empty)
    );

    full_checker #(ADDR_SIZE) w_full_checker (
        .w_clk(w_clk),
        .w_rst(w_rst),
        .w_en(w_en),
        .w_full(w_full),
        .w_addr(w_addr),
        .w_ptr_gray(w_ptr_i),
        .r_ptr_gray(r_ptr_o)
    );

    fifo_mem #(ADDR_SIZE, DATA_SIZE) fifo_mem (
        .w_clk(w_clk),
        .w_en(w_en),
        .w_full(w_full),
        .w_addr(w_addr),
        .w_data(w_data),
        .r_addr(r_addr),
        .r_data(r_data)
    );

endmodule

Asyn_Fifo/DUT/simple_demo_tb.sv
`timescale 1ns/1ps


module simple_demo_tb(
    input logic w_clk, w_rst, w_en,
    input logic r_clk, r_rst, r_en,
    input logic [DATA_SIZE-1 : 0] w_data,
    output logic [DATA_SIZE-1 : 0] r_data,
    output logic w_full, r_empty
);
    
    parameter DATA_SIZE = 8;
    parameter ADDR_SIZE = 4;

    async_fifo #(
        .DATA_SIZE(DATA_SIZE),
        .ADDR_SIZE(ADDR_SIZE)
    ) dut (
        .w_full(w_full),
        .w_en(w_en),
        .w_clk(w_clk),
        .w_rst(w_rst),
        .w_data(w_data),

        .r_empty(r_empty),
        .r_en(r_en),
        .r_clk(r_clk),
        .r_rst(r_rst),
        .r_data(r_data)
    );
    /*
    initial begin
        w_clk = 0;
        r_clk = 0;
        forever begin
            #5 w_clk = !w_clk;
            #7 r_clk = !r_clk;
        end
    end
    

    initial begin
        r_clk = 0;
        r_rst = 1;    
        // repeat(5) @ (posedge r_clk);
        repeat (5) #7;
        r_rst = 0;
        // repeat(5) @ (posedge r_clk);
        #35;
        r_rst = 1;
    end
    
    initial begin
        w_clk = 0;
        w_rst = 1;
        #25;
        w_rst = 0;
        #25;
        w_rst = 1;
    end

    initial begin
        logic [7 : 0] random_data;
        w_data = 0;
        w_en   = 0;
        r_en   = 0;
        for (int i=0; i<40; i++) begin
            random_data = $random % 256;
            write_data(random_data);
            if (i%2 == 0) begin
                read_data();
            end
        end

        for (int i = 0; i < 20; i++) begin
            read_data();
        end

        $finish;
    end

    task write_data;
        input [DATA_SIZE-1 : 0] data;
        begin
            // @ (posedge w_clk);
            // #5;
            wait_w_clock_cycles(1);
            if(!w_full) begin
                w_en = 1;
                w_data = data;
            end
            //@(posedge w_clk);
            // #5;
            wait_w_clock_cycles(1);
            w_en = 0;
        end
    endtask

    task read_data;
        begin
            @ (posedge r_clk);
            //wait_w_clock_cycles(1);
            if(!r_empty) begin
                r_en = 1;
            end
            //@ (posedge r_clk);
            //#7;
            r_en = 0;
        end
    endtask


    // Task to wait for a specific number of clock cycles
    task wait_w_clock_cycles(input int num_cycles);
        int count;
        begin
            for (count = 0; count < num_cycles; count++) begin
                @(posedge w_clk);
            end
        end
    endtask
    */
endmodule

Asyn_Fifo/DUT/output.vcd
$version Generated by VerilatedVcd $end
$date Sat Apr 13 17:29:54 2024
 $end
$timescale   1ps $end

 $scope module TOP $end
  $var wire  1 G r_clk $end
  $var wire  8 K r_data [7:0] $end
  $var wire  1 M r_empty $end
  $var wire  1 I r_en $end
  $var wire  1 H r_rst $end
  $var wire  1 D w_clk $end
  $var wire  8 J w_data [7:0] $end
  $var wire  1 F w_en $end
  $var wire  1 L w_full $end
  $var wire  1 E w_rst $end
  $scope module simple_demo_tb $end
   $var wire 32 O ADDR_SIZE [31:0] $end
   $var wire 32 N DATA_SIZE [31:0] $end
   $var wire  1 G r_clk $end
   $var wire  8 K r_data [7:0] $end
   $var wire  1 M r_empty $end
   $var wire  1 I r_en $end
   $var wire  1 H r_rst $end
   $var wire  1 D w_clk $end
   $var wire  8 J w_data [7:0] $end
   $var wire  1 F w_en $end
   $var wire  1 L w_full $end
   $var wire  1 E w_rst $end
   $scope module dut $end
    $var wire 32 O ADDR_SIZE [31:0] $end
    $var wire 32 N DATA_SIZE [31:0] $end
    $var wire  4 # r_addr [3:0] $end
    $var wire  1 G r_clk $end
    $var wire  8 K r_data [7:0] $end
    $var wire  1 M r_empty $end
    $var wire  1 I r_en $end
    $var wire  5 $ r_ptr_i [4:0] $end
    $var wire  5 % r_ptr_o [4:0] $end
    $var wire  1 H r_rst $end
    $var wire  4 ( w_addr [3:0] $end
    $var wire  1 D w_clk $end
    $var wire  8 J w_data [7:0] $end
    $var wire  1 F w_en $end
    $var wire  1 L w_full $end
    $var wire  5 ) w_ptr_i [4:0] $end
    $var wire  5 * w_ptr_o [4:0] $end
    $var wire  1 E w_rst $end
    $scope module fifo_mem $end
     $var wire 32 O ADDR_SIZE [31:0] $end
     $var wire 32 N DATA_SIZE [31:0] $end
     $var wire 32 P DEPTH [31:0] $end
     $var wire  8 4 fifo_data(0) [7:0] $end
     $var wire  8 5 fifo_data(1) [7:0] $end
     $var wire  8 > fifo_data(10) [7:0] $end
     $var wire  8 ? fifo_data(11) [7:0] $end
     $var wire  8 @ fifo_data(12) [7:0] $end
     $var wire  8 A fifo_data(13) [7:0] $end
     $var wire  8 B fifo_data(14) [7:0] $end
     $var wire  8 C fifo_data(15) [7:0] $end
     $var wire  8 6 fifo_data(2) [7:0] $end
     $var wire  8 7 fifo_data(3) [7:0] $end
     $var wire  8 8 fifo_data(4) [7:0] $end
     $var wire  8 9 fifo_data(5) [7:0] $end
     $var wire  8 : fifo_data(6) [7:0] $end
     $var wire  8 ; fifo_data(7) [7:0] $end
     $var wire  8 < fifo_data(8) [7:0] $end
     $var wire  8 = fifo_data(9) [7:0] $end
     $var wire  4 # r_addr [3:0] $end
     $var wire  8 K r_data [7:0] $end
     $var wire  4 ( w_addr [3:0] $end
     $var wire  1 D w_clk $end
     $var wire  8 J w_data [7:0] $end
     $var wire  1 F w_en $end
     $var wire  1 L w_full $end
    $upscope $end
    $scope module r_empty_checker $end
     $var wire 32 O ADDR_SIZE [31:0] $end
     $var wire  4 # r_addr [3:0] $end
     $var wire  1 G r_clk $end
     $var wire  1 M r_empty $end
     $var wire  1 / r_empty_tmp $end
     $var wire  1 I r_en $end
     $var wire  5 ' r_ptr_bin [4:0] $end
     $var wire  5 . r_ptr_bin_next [4:0] $end
     $var wire  5 $ r_ptr_gray [4:0] $end
     $var wire  5 - r_ptr_gray_next [4:0] $end
     $var wire  1 H r_rst $end
     $var wire  5 * w_ptr_gray [4:0] $end
    $upscope $end
    $scope module r_sync $end
     $var wire 32 O ADDR_SIZE [31:0] $end
     $var wire  1 G clk $end
     $var wire  5 $ i_ptr [4:0] $end
     $var wire  5 % o_ptr [4:0] $end
     $var wire  5 & ptr_temp [4:0] $end
     $var wire  1 H rst $end
    $upscope $end
    $scope module w_full_checker $end
     $var wire 32 O ADDR_SIZE [31:0] $end
     $var wire  5 % r_ptr_gray [4:0] $end
     $var wire  5 1 r_ptr_gray_next [4:0] $end
     $var wire  4 ( w_addr [3:0] $end
     $var wire  1 D w_clk $end
     $var wire  1 F w_en $end
     $var wire  1 L w_full $end
     $var wire  1 2 w_full_tmp $end
     $var wire  5 , w_ptr_bin [4:0] $end
     $var wire  5 3 w_ptr_bin_next [4:0] $end
     $var wire  5 ) w_ptr_gray [4:0] $end
     $var wire  5 0 w_ptr_gray_next [4:0] $end
     $var wire  1 E w_rst $end
    $upscope $end
    $scope module w_sync $end
     $var wire 32 O ADDR_SIZE [31:0] $end
     $var wire  1 D clk $end
     $var wire  5 ) i_ptr [4:0] $end
     $var wire  5 * o_ptr [4:0] $end
     $var wire  5 + ptr_temp [4:0] $end
     $var wire  1 E rst $end
    $upscope $end
   $upscope $end
  $upscope $end
 $upscope $end
$enddefinitions $end


#0
b0000 #
b00000 $
b00000 %
b00000 &
b00000 '
b0000 (
b00000 )
b00000 *
b00000 +
b00000 ,
b00000 -
b00000 .
1/
b00000 0
b11000 1
02
b00000 3
b00000000 4
b00000000 5
b00000000 6
b00000000 7
b00000000 8
b00000000 9
b00000000 :
b00000000 ;
b00000000 <
b00000000 =
b00000000 >
b00000000 ?
b00000000 @
b00000000 A
b00000000 B
b00000000 C
0D
1E
0F
0G
1H
0I
b00000000 J
b00000000 K
0L
0M
b00000000000000000000000000001000 N
b00000000000000000000000000000100 O
b00000000000000000000000000010000 P
#1
#2
0H
1M
#3
#4
#5
b00001 0
b00001 3
b10001101 4
1D
1F
b10001101 J
b10001101 K
#6
0E
#7
1G
#8
#9
#10
0D
#11
#12
#13
#14
0G
#15
b01100011 4
1D
b01100011 J
b01100011 K
#16
1E
#17
#18
#19
#20
0D
#21
1G
#22
1H
#23
#24
#25
b0001 (
b00001 )
b00001 ,
b00011 0
b00010 3
b01101010 5
1D
b01101010 J
#26
#27
#28
0G
#29
#30
0D
#31
#32
#33
#34
#35
b0010 (
b00011 )
b00001 +
b00010 ,
b00010 0
b00011 3
b11011111 6
1D
1G
b11011111 J
#36
#37
#38
#39
#40
0D
#41
#42
0G
#43
#44
#45
b0011 (
b00010 )
b00001 *
b00011 +
b00011 ,
0/
b00110 0
b00100 3
b01110000 7
1D
b01110000 J
#46
#47
#48
#49
1G
0M
#50
0D
#51
#52
#53
#54
#55
b0100 (
b00110 )
b00011 *
b00010 +
b00100 ,
b00111 0
b00101 3
b00011111 8
1D
b00011111 J
#56
0G
#57
#58
#59
#60
0D
#61
#62
#63
b00001 -
b00001 .
1G
1I
#64
#65
b0101 (
b00111 )
b00010 *
b00110 +
b00101 ,
1D
0F
#66
#67
#68
#69
#70
0D
0G
#71
#72
#73
#74
#75
b00110 *
b00111 +
1D
#76
#77
b0001 #
b00001 $
b00001 '
1G
0I
b01101010 K
#78
#79
#80
0D
#81
#82
#83
#84
0G
#85
b00111 *
b00101 0
b00110 3
b00001110 9
1D
1F
b00001110 J
#86
#87
#88
#89
#90
0D
#91
b00001 &
1G
#92
#93
#94
#95
b0110 (
b00101 )
b00110 ,
b00100 0
b00111 3
b01110110 :
1D
b01110110 J
#96
#97
#98
0G
#99
#100
0D
#101
#102
#103
#104
#105
b00001 %
b0111 (
b00100 )
b00101 +
b00111 ,
b01100 0
b11001 1
b01000 3
b00100011 ;
1D
1G
b00100011 J
#106
#107
#108
#109
#110
0D
#111
#112
0G
#113
#114
#115
b1000 (
b01100 )
b00101 *
b00100 +
b01000 ,
b01101 0
b01001 3
b01011001 <
1D
b01011001 J
#116
#117
#118
#119
1G
#120
0D
#121
#122
#123
#124
#125
b1001 (
b01101 )
b00100 *
b01100 +
b01001 ,
1D
0F
#126
0G
#127
#128
#129
#130
0D
#131
#132
#133
1G
#134
#135
b01100 *
b01101 +
b01111 0
b01010 3
b11101101 =
1D
1F
b11101101 J
#136
#137
#138
#139
#140
0D
0G
#141
#142
#143
#144
#145
b1010 (
b01111 )
b01101 *
b01010 ,
1D
0F
#146
#147
1G
#148
#149
#150
0D
#151
#152
#153
#154
0G
#155
b01111 +
b01110 0
b01011 3
b10110011 >
1D
1F
b10110011 J
#156
#157
#158
#159
#160
0D
#161
b00011 -
b00010 .
1G
1I
#162
#163
#164
#165
b1011 (
b01110 )
b01111 *
b01011 ,
1D
0F
#166
#167
#168
0G
#169
#170
0D
#171
#172
#173
#174
#175
b0010 #
b00011 $
b00010 '
b01110 +
1D
1G
0I
b11011111 K
#176
#177
#178
#179
#180
0D
#181
#182
0G
#183
#184
#185
b01110 *
1D
#186
#187
#188
#189
b00011 &
1G
#190
0D
#191
#192
#193
#194
#195
1D
#196
0G
#197
#198
#199
#200
0D
#201
#202
#203
b00011 %
b00010 -
b00011 .
b11011 1
1G
1I
#204
#205
1D
#206
#207
#208
#209
#210
0D
0G
#211
#212
#213
#214
#215
b01010 0
b01100 3
b01011010 ?
1D
1F
b01011010 J
#216
#217
b0011 #
b00010 $
b00011 '
1G
0I
b01110000 K
#218
#219
#220
0D
#221
#222
#223
#224
0G
#225
b1100 (
b01010 )
b01100 ,
b01011 0
b01101 3
b01101000 @
1D
b01101000 J
#226
#227
#228
#229
#230
0D
#231
b00010 &
1G
#232
#233
#234
#235
b1101 (
b01011 )
b01010 +
b01101 ,
b01001 0
b01110 3
b11011110 A
1D
b11011110 J
#236
#237
#238
0G
#239
#240
0D
#241
#242
#243
#244
#245
b00010 %
b1110 (
b01001 )
b01010 *
b01011 +
b01110 ,
b00110 -
b00100 .
b11010 1
1D
0F
1G
1I
#246
#247
#248
#249
#250
0D
#251
#252
0G
#253
#254
#255
b01011 *
b01001 +
1D
#256
#257
#258
#259
b0100 #
b00110 $
b00100 '
b00111 -
b00101 .
1G
b00011111 K
#260
0D
#261
#262
#263
#264
#265
b01001 *
1D
#266
0G
#267
#268
#269
#270
0D
#271
#272
#273
b0101 #
b00111 $
b00110 &
b00101 '
b00101 -
b00110 .
1G
b00001110 K
#274
#275
1D
#276
#277
#278
#279
#280
0D
0G
#281
#282
#283
#284
#285
1D
#286
#287
b0110 #
b00101 $
b00110 %
b00111 &
b00110 '
b00100 -
b00111 .
b11110 1
1G
b01110110 K
#288
#289
#290
0D
#291
#292
#293
#294
0G
#295
b01000 0
b01111 3
1D
1F
b00000000 J
#296
#297
#298
#299
#300
0D
#301
b0111 #
b00100 $
b00111 %
b00101 &
b00111 '
b11111 1
1G
0I
b00100011 K
#302
#303
#304
#305
b1111 (
b01000 )
b01111 ,
b11000 0
b10000 3
b10110011 C
1D
b10110011 J
#306
#307
#308
0G
#309
#310
0D
#311
#312
#313
#314
#315
b00101 %
b00100 &
b0000 (
b11000 )
b01000 +
b10000 ,
b11101 1
1D
0F
1G
#316
#317
#318
#319
#320
0D
#321
#322
0G
#323
#324
#325
b01000 *
b11000 +
b11001 0
b10001 3
b00111100 4
1D
1F
b00111100 J
#326
#327
#328
#329
b00100 %
b11100 1
1G
#330
0D
#331
#332
#333
#334
#335
b0001 (
b11001 )
b11000 *
b10001 ,
b11011 0
b10010 3
b00011111 5
1D
b00011111 J
#336
0G
#337
#338
#339
#340
0D
#341
#342
#343
b01100 -
b01000 .
1G
1I
#344
#345
b0010 (
b11011 )
b11001 +
b10010 ,
1D
0F
#346
#347
#348
#349
#350
0D
0G
#351
#352
#353
#354
#355
b11001 *
b11011 +
1D
#356
#357
b1000 #
b01100 $
b01000 '
1G
0I
b01011001 K
#358
#359
#360
0D
#361
#362
#363
#364
0G
#365
b11011 *
1D
#366
#367
#368
#369
#370
0D
#371
b01100 &
1G
#372
#373
#374
#375
b11010 0
b10011 3
b11001110 6
1D
1F
b11001110 J
#376
#377
#378
0G
#379
#380
0D
#381
#382
#383
#384
#385
b01100 %
b0011 (
b11010 )
b10011 ,
b01101 -
b01001 .
b10100 1
1D
0F
1G
1I
#386
#387
#388
#389
#390
0D
#391
#392
0G
#393
#394
#395
b11010 +
1D
#396
#397
#398
#399
b1001 #
b01101 $
b01001 '
1G
0I
b11101101 K
#400
0D
#401
#402
#403
#404
#405
b11010 *
b11110 0
b10100 3
b10000111 7
1D
1F
b10000111 J
#406
0G
#407
#408
#409
#410
0D
#411
#412
#413
b01101 &
b01111 -
b01010 .
1G
1I
#414
#415
b0100 (
b11110 )
b10100 ,
b11111 0
b10101 3
b01100000 8
1D
b01100000 J
#416
#417
#418
#419
#420
0D
0G
#421
#422
#423
#424
#425
b0101 (
b11111 )
b11110 +
b10101 ,
1D
0F
#426
#427
b1010 #
b01111 $
b01101 %
b01010 '
b10101 1
1G
0I
b10110011 K
#428
#429
#430
0D
#431
#432
#433
#434
0G
#435
b11110 *
b11111 +
1D
#436
#437
#438
#439
#440
0D
#441
b01111 &
1G
#442
#443
#444
#445
b11111 *
b11101 0
b10110 3
b10111011 9
1D
1F
b10111011 J
#446
#447
#448
0G
#449
#450
0D
#451
#452
#453
#454
#455
b01111 %
b0110 (
b11101 )
b10110 ,
b10111 1
1D
0F
1G
#456
#457
#458
#459
#460
0D
#461
#462
0G
#463
#464
#465
b11101 +
1D
#466
#467
#468
#469
1G
#470
0D
#471
#472
#473
#474
#475
b11101 *
1D
#476
0G
#477
#478
#479
#480
0D
#481
#482
#483
1G
#484
#485
1D
#486
#487
#488
#489
#490
0D
0G
#491
#492
#493
#494
#495
b11100 0
b10111 3
b11111001 :
1D
1F
b11111001 J
#496
#497
1G
#498
#499
#500
0D
#501
#502
#503
#504
0G
#505
b0111 (
b11100 )
b10111 ,
1D
0F
#506
#507
#508
#509
#510
0D
#511
1G
#512
#513
#514
#515
b11100 +
b10100 0
b11000 3
b10001110 ;
1D
1F
b10001110 J
#516
#517
#518
0G
#519
#520
0D
#521
#522
#523
#524
#525
b1000 (
b10100 )
b11100 *
b11000 ,
1D
0F
1G
#526
#527
#528
#529
#530
0D
#531
#532
0G
#533
#534
#535
b10100 +
b10101 0
b11001 3
b10001001 <
1D
1F
b10001001 J
#536
#537
#538
#539
1G
#540
0D
#541
#542
#543
#544
#545
b1001 (
b10101 )
b10100 *
b11001 ,
1D
0F
#546
0G
#547
#548
#549
#550
0D
#551
#552
#553
1G
#554
#555
b10101 +
1D
#556
#557
#558
#559
#560
0D
0G
#561
#562
#563
#564
#565
b10101 *
b10111 0
12
b11010 3
b01111101 =
1D
1F
b01111101 J
#566
#567
1G
#568
#569
#570
0D
#571
#572
#573
#574
0G
#575
b1010 (
b10111 )
b11010 ,
1D
0F
1L
#576
#577
#578
#579
#580
0D
#581
1G
#582
#583
#584
#585
b10111 +
1D
1F
b00000101 J
#586
#587
#588
0G
#589
#590
0D
#591
#592
#593
#594
#595
b10111 *
b01110 -
b01011 .
1D
1G
1I
b00011100 J
#596
#597
#598
#599
#600
0D
#601
#602
0G
#603
#604
#605
1D
0F
#606
#607
#608
#609
b1011 #
b01110 $
b01011 '
1G
0I
b01011010 K
#610
0D
#611
#612
#613
#614
#615
1D
#616
0G
#617
#618
#619
#620
0D
#621
#622
#623
b01110 &
1G
#624
#625
1D
1F
b00000011 J
#626
#627
#628
#629
#630
0D
0G
#631
#632
#633
#634
#635
1D
0F
#636
#637
b01110 %
b10110 1
02
1G
#638
#639
#640
0D
#641
#642
#643
#644
0G
#645
b10110 0
12
b11011 3
b01010101 >
1D
1F
b01010101 J
0L
#646
#647
#648
#649
#650
0D
#651
1G
#652
#653
#654
#655
b1011 (
b10110 )
b11011 ,
1D
b11100011 J
1L
#656
#657
#658
0G
#659
#660
0D
#661
#662
#663
#664
#665
b10110 +
b01010 -
b01100 .
1D
0F
1G
1I
#666
#667
#668
#669
#670
0D
#671
#672
0G
#673
#674
#675
b10110 *
1D
#676
#677
#678
#679
b1100 #
b01010 $
b01100 '
1G
0I
b01101000 K
#680
0D
#681
#682
#683
#684
#685
1D
#686
0G
#687
#688
#689
#690
0D
#691
#692
#693
b01010 &
1G
#694
#695
1D
1F
b00101010 J
#696
#697
#698
#699
#700
0D
0G
#701
#702
#703
#704
#705
1D
0F
#706
#707
b01010 %
b10010 1
02
1G
#708
#709
#710
0D
#711
#712
#713
#714
0G
#715
b10010 0
12
b11100 3
b10000010 ?
1D
1F
b10000010 J
0L
#716
#717
#718
#719
#720
0D
#721
1G
#722
#723
#724
#725
b1100 (
b10010 )
b11100 ,
1D
b10000111 J
1L
#726
#727
#728
0G
#729
#730
0D
#731
#732
#733
#734
#735
b10010 +
b01011 -
b01101 .
1D
0F
1G
1I
#736
#737
#738
#739
#740
0D
#741
#742
0G
#743
#744
#745
b10010 *
1D
#746
#747
#748
#749
b1101 #
b01011 $
b01101 '
1G
0I
b11011110 K
#750
0D
#751
#752
#753
#754
#755
1D
1F
b11010111 J
#756
0G
#757
#758
#759
#760
0D
#761
#762
#763
b01011 &
b01001 -
b01110 .
1G
1I
#764
#765
1D
b11011010 J
#766
#767
#768
#769
#770
0D
0G
#771
#772
#773
#774
#775
1D
0F
#776
#777
b1110 #
b01001 $
b01011 %
b01110 '
b01000 -
b01111 .
b10011 1
02
1G
b00000000 K
#778
#779
#780
0D
#781
#782
#783
#784
0G
#785
b10011 0
12
b11101 3
b01100110 @
1D
1F
b01100110 J
0L
#786
#787
#788
#789
#790
0D
#791
b1111 #
b01000 $
b01001 &
b01111 '
1G
0I
b10110011 K
#792
#793
#794
#795
b1101 (
b10011 )
b11101 ,
1D
b01001010 J
1L
#796
#797
#798
0G
#799
#800
0D
#801
#802
#803
#804
#805
b01001 %
b01000 &
b10011 +
b10001 1
02
1D
1G
b10111110 J
#806
#807
#808
#809
#810
0D
#811
#812
0G
#813
#814
#815
b10011 *
1D
0F
0L
#816
#817
#818
#819
b01000 %
b10000 1
1G
#820
0D
#821
#822
#823
#824
#825
b10001 0
b11110 3
b00101111 A
1D
1F
b00101111 J
#826
0G
#827
#828
#829
#830
0D
#831
#832
#833
1G
#834
#835
b1110 (
b10001 )
b11110 ,
1D
0F
#836
#837
#838
#839
#840
0D
0G
#841
#842
#843
#844
#845
b10001 +
1D
#846
#847
1G
#848
#849
#850
0D
#851
#852
#853
#854
0G
#855
b10001 *
b10000 0
12
b11111 3
b10001111 B
1D
1F
b10001111 J
#856
#857
#858
#859
#860
0D
#861
1G
#862
#863
#864
#865
b1111 (
b10000 )
b11111 ,
1D
0F
1L
#866
#867
#868
0G
#869
#870
0D
#871
#872
#873
#874
#875
b10000 +
1D
1F
1G
b01000011 J
#876
#877
#878
#879
#880
0D
#881
#882
0G
#883
#884
#885
b10000 *
1D
0F
#886
#887
#888
#889
1G
#890
0D
#891
#892
#893
#894
#895
1D
1F
b10010101 J
#896
0G
#897
#898
#899
#900
0D
#901
#902
#903
1G
#904
#905
1D
b10100111 J
#906
#907
#908
#909
#910
0D
0G
#911
#912
#913
#914
#915
1D
0F
#916
#917
1G
#918
#919
#920
0D
#921
#922
#923
#924
0G
#925
1D
#926
#927
#928
#929
#930
0D
#931
b11000 -
b10000 .
1G
1I
#932
#933
#934
#935
1D
1F
b01010111 J
#936
#937
#938
0G
#939
#940
0D
#941
#942
#943
#944
#945
b0000 #
b11000 $
b10000 '
1D
1G
0I
b01000010 J
b00111100 K
#946
#947
#948
#949
#950
0D
#951
#952
0G
#953
#954
#955
1D
0F
#956
#957
#958
#959
b11000 &
1G
#960
0D
#961
#962
#963
#964
#965
1D
#966
0G
#967
#968
#969
#970
0D
#971
#972
#973
b11000 %
b11001 -
b10001 .
b00000 1
02
1G
1I
#974
#975
1D
0L
#976
#977
#978
#979
#980
0D
0G
#981
#982
#983
#984
#985
1D
#986
#987
b0001 #
b11001 $
b10001 '
1G
0I
b00011111 K
#988
#989
#990
0D
#991
#992
#993
#994
0G
#995
1D
#996
#997
#998
#999
#1000
0D
#1001
b11001 &
1G
#1002
#1003
#1004
#1005
1D
#1006
#1007
#1008
0G
#1009
#1010
0D
#1011
#1012
#1013
#1014
#1015
b11001 %
b00000 0
b00001 1
b00000 3
b11000000 C
1D
1F
1G
b11000000 J
#1016
#1017
#1018
#1019
#1020
0D
#1021
#1022
0G
#1023
#1024
#1025
b0000 (
b00000 )
b00000 ,
1D
0F
#1026
#1027
#1028
#1029
1G
#1030
0D
#1031
#1032
#1033
#1034
#1035
b00000 +
1D
#1036
0G
#1037
#1038
#1039
#1040
0D
#1041
#1042
#1043
b11011 -
b10010 .
1G
1I
#1044
#1045
b00000 *
1D
#1046
#1047
#1048
#1049
#1050
0D
0G
#1051
#1052
#1053
#1054
#1055
b00001 0
12
b00001 3
b10111001 4
1D
1F
b10111001 J
#1056
#1057
b0010 #
b11011 $
b10010 '
1G
0I
b11001110 K
#1058
#1059
#1060
0D
#1061
#1062
#1063
#1064
0G
#1065
b0001 (
b00001 )
b00001 ,
1D
0F
1L
#1066
#1067
#1068
#1069
#1070
0D
#1071
b11011 &
1G
#1072
#1073
#1074
#1075
b00001 +
1D
#1076
#1077
#1078
0G
#1079
#1080
0D
#1081
#1082
#1083
#1084
#1085
b11011 %
b00001 *
b00011 1
02
1D
1G
#1086
#1087
#1088
#1089
#1090
0D
