Asyn_Fifo/DUT/fifo_mem.sv
`timescale 1ns/1ps
module fifo_mem #(
    parameter ADDR_SIZE = 4,
    parameter DATA_SIZE = 8
) (
    output logic [DATA_SIZE-1 : 0] r_data,
    input [ADDR_SIZE-1 : 0] r_addr,
    input [DATA_SIZE-1 : 0] w_data,
    input w_en,
    input w_clk,
    input w_full,
    input [ADDR_SIZE-1 : 0] w_addr
);

    localparam DEPTH = 1 << ADDR_SIZE;
    logic [DATA_SIZE-1 : 0] fifo_data [0 : DEPTH-1];

    //always @(posedge w_clk) begin
    always @(*) begin
        if(w_en && !w_full) begin
            fifo_data[w_addr] = w_data;
        end
    end

    always @(*) begin
        r_data = fifo_data[r_addr];
    end

endmodule

Asyn_Fifo/DUT/full_checker.sv
// `timescale 1ns/1ps
module full_checker #(
    ADDR_SIZE = 4
) (
    w_en,
    w_clk,
    w_rst,
    w_full,
    w_addr,
    w_ptr_gray,
    r_ptr_gray
);

input [ADDR_SIZE : 0] r_ptr_gray; // from sync from empty
input w_clk;
input w_rst;
input w_en;

output logic [ADDR_SIZE-1 : 0] w_addr;
output logic w_full;
output logic [ADDR_SIZE : 0] w_ptr_gray; // to sync to empty

logic [ADDR_SIZE : 0]   w_ptr_gray_next;
logic [ADDR_SIZE : 0]   r_ptr_gray_next;
logic                   w_full_tmp;
//logic [ADDR_SIZE-1 : 0] w_addr_tmp;
logic [ADDR_SIZE : 0]   w_ptr_bin;
logic [ADDR_SIZE : 0]   w_ptr_bin_next;


always @(posedge w_clk or negedge w_rst) begin
    if(!w_rst) begin
        // w_addr     <= 0;
        w_ptr_gray <= 0;
        w_full     <= 0;
        w_ptr_bin  <= 0;
    end
    else begin
        // w_addr      <= w_addr_tmp;
        w_ptr_gray  <= w_ptr_gray_next;
        w_full      <= w_full_tmp;
        w_ptr_bin   <= w_ptr_bin_next;
    end
end

always @* begin
    // w_addr_tmp = w_ptr_bin[ADDR_SIZE-1 : 0]; // current address
    w_addr = w_ptr_bin[ADDR_SIZE-1 : 0];
    w_ptr_bin_next = w_ptr_bin + ({4'b0000, !w_full} & {4'b0000, w_en}); // move the w_ptr
    w_ptr_gray_next = w_ptr_bin_next ^ (w_ptr_bin_next >> 1); //convert to gray code
    r_ptr_gray_next = {~r_ptr_gray[ADDR_SIZE : ADDR_SIZE-1], r_ptr_gray[ADDR_SIZE-2 : 0]};
    if(w_ptr_gray_next == r_ptr_gray_next) begin
        w_full_tmp = 1;
    end
    else begin
        w_full_tmp = 0;
    end
end

endmodule

Asyn_Fifo/DUT/empty_checker.sv
// `timescale 1ns/1ps

module empty_checker #(
    parameter ADDR_SIZE = 4
) (
    r_empty,
    r_ptr_gray,
    r_addr,
    w_ptr_gray,
    r_en,
    r_clk,
    r_rst
);

    output logic                   r_empty;
    output logic [ADDR_SIZE : 0]   r_ptr_gray;
    output logic [ADDR_SIZE-1 : 0] r_addr;

    input  [ADDR_SIZE : 0]   w_ptr_gray;
    input                    r_en;
    input                    r_clk;
    input                    r_rst;

    logic [ADDR_SIZE : 0]   r_ptr_gray_next;
    logic [ADDR_SIZE : 0]   r_ptr_bin;
    logic [ADDR_SIZE : 0]   r_ptr_bin_next;
    // logic [ADDR_SIZE-1 : 0] r_addr_tmp;
    logic                   r_empty_tmp;

    always @(posedge r_clk or negedge r_rst) begin
        if(!r_rst) begin
            r_empty    <= 1;
            r_ptr_gray <= 0;
            // r_addr     <= 0;
            r_ptr_bin  <= 0;
        end
        else begin
            r_empty     <= r_empty_tmp;
            r_ptr_gray  <= r_ptr_gray_next;
            // r_addr      <= r_addr_tmp;
            r_ptr_bin   <= r_ptr_bin_next;
        end
    end

    always @(*) begin

        // r_addr_tmp = r_ptr_bin[ADDR_SIZE-1 : 0];
        r_addr = r_ptr_bin[ADDR_SIZE-1 : 0];
        r_ptr_bin_next = r_ptr_bin + ({4'b0000, !r_empty} & {4'b0000, r_en});
        r_ptr_gray_next = r_ptr_bin_next ^ (r_ptr_bin_next >> 1);

        if(r_ptr_gray_next == w_ptr_gray) begin
            r_empty_tmp = 1;
        end
        else begin
            r_empty_tmp = 0;
        end
    end

endmodule

Asyn_Fifo/DUT/sync_2ff.sv
// `timescale 1ns/1ps
module sync_2ff #(
    parameter ADDR_SIZE = 4
) (
    o_ptr,
    i_ptr,
    clk,
    rst
);
    input  [ADDR_SIZE : 0] i_ptr;
    output logic [ADDR_SIZE : 0] o_ptr;
    input clk;
    input rst;

    logic [ADDR_SIZE : 0] ptr_temp;

    always @(posedge clk or negedge rst) begin
        if(rst != 1) begin
            ptr_temp <= 0;
            o_ptr <= 0;
        end else begin
            ptr_temp <= i_ptr;
            o_ptr <= ptr_temp;
        end
    end
endmodule

Asyn_Fifo/DUT/async_fifo.sv
`timescale 1ns/1ps

module async_fifo #(
    parameter DATA_SIZE = 8,
    parameter ADDR_SIZE  = 4
) (
    w_full, 
    w_data,
    w_en,
    w_clk,
    w_rst,

    r_en,
    r_clk,
    r_rst,
    r_data,
    r_empty
);

    output logic [DATA_SIZE-1 : 0] r_data;
    output logic                  w_full;
    output logic                  r_empty;

    input [DATA_SIZE-1 : 0]  w_data;
    input                    w_en;
    input                    w_rst;
    input                    w_clk;
    input                    r_en;
    input                    r_clk;
    input                    r_rst;

    logic [ADDR_SIZE-1 : 0]   w_addr;
    logic [ADDR_SIZE-1 : 0]   r_addr;
    logic [ADDR_SIZE : 0]     w_ptr_i;
    logic [ADDR_SIZE : 0]     r_ptr_i;
    logic [ADDR_SIZE : 0]     w_ptr_o;
    logic [ADDR_SIZE : 0]     r_ptr_o;

    sync_2ff #(ADDR_SIZE) r_sync (
        .i_ptr(r_ptr_i),
        .o_ptr(r_ptr_o),
        .clk(r_clk),
        .rst(r_rst)
    );

    sync_2ff #(ADDR_SIZE) w_sync (
        .i_ptr(w_ptr_i),
        .o_ptr(w_ptr_o),
        .clk(w_clk),
        .rst(w_rst)
    );
    
    empty_checker #(ADDR_SIZE) r_empty_checker (
        .r_clk(r_clk),
        .r_en(r_en),
        .r_rst(r_rst),
        .r_addr(r_addr),
        .r_ptr_gray(r_ptr_i),
        .w_ptr_gray(w_ptr_o),
        .r_empty(r_empty)
    );

    full_checker #(ADDR_SIZE) w_full_checker (
        .w_clk(w_clk),
        .w_rst(w_rst),
        .w_en(w_en),
        .w_full(w_full),
        .w_addr(w_addr),
        .w_ptr_gray(w_ptr_i),
        .r_ptr_gray(r_ptr_o)
    );

    fifo_mem #(ADDR_SIZE, DATA_SIZE) fifo_mem (
        .w_clk(w_clk),
        .w_en(w_en),
        .w_full(w_full),
        .w_addr(w_addr),
        .w_data(w_data),
        .r_addr(r_addr),
        .r_data(r_data)
    );

endmodule

Asyn_Fifo/DUT/simple_demo_tb.sv
`timescale 1ns/1ps


module simple_demo_tb(
    input logic w_clk, w_rst, w_en,
    input logic r_clk, r_rst, r_en,
    input logic [DATA_SIZE-1 : 0] w_data,
    output logic [DATA_SIZE-1 : 0] r_data,
    output logic w_full, r_empty
);
    
    parameter DATA_SIZE = 8;
    parameter ADDR_SIZE = 4;

    async_fifo #(
        .DATA_SIZE(DATA_SIZE),
        .ADDR_SIZE(ADDR_SIZE)
    ) dut (
        .w_full(w_full),
        .w_en(w_en),
        .w_clk(w_clk),
        .w_rst(w_rst),
        .w_data(w_data),

        .r_empty(r_empty),
        .r_en(r_en),
        .r_clk(r_clk),
        .r_rst(r_rst),
        .r_data(r_data)
    );
    /*
    initial begin
        w_clk = 0;
        r_clk = 0;
        forever begin
            #5 w_clk = !w_clk;
            #7 r_clk = !r_clk;
        end
    end
    

    initial begin
        r_clk = 0;
        r_rst = 1;    
        // repeat(5) @ (posedge r_clk);
        repeat (5) #7;
        r_rst = 0;
        // repeat(5) @ (posedge r_clk);
        #35;
        r_rst = 1;
    end
    
    initial begin
        w_clk = 0;
        w_rst = 1;
        #25;
        w_rst = 0;
        #25;
        w_rst = 1;
    end

    initial begin
        logic [7 : 0] random_data;
        w_data = 0;
        w_en   = 0;
        r_en   = 0;
        for (int i=0; i<40; i++) begin
            random_data = $random % 256;
            write_data(random_data);
            if (i%2 == 0) begin
                read_data();
            end
        end

        for (int i = 0; i < 20; i++) begin
            read_data();
        end

        $finish;
    end

    task write_data;
        input [DATA_SIZE-1 : 0] data;
        begin
            // @ (posedge w_clk);
            // #5;
            wait_w_clock_cycles(1);
            if(!w_full) begin
                w_en = 1;
                w_data = data;
            end
            //@(posedge w_clk);
            // #5;
            wait_w_clock_cycles(1);
            w_en = 0;
        end
    endtask

    task read_data;
        begin
            @ (posedge r_clk);
            //wait_w_clock_cycles(1);
            if(!r_empty) begin
                r_en = 1;
            end
            //@ (posedge r_clk);
            //#7;
            r_en = 0;
        end
    endtask


    // Task to wait for a specific number of clock cycles
    task wait_w_clock_cycles(input int num_cycles);
        int count;
        begin
            for (count = 0; count < num_cycles; count++) begin
                @(posedge w_clk);
            end
        end
    endtask
    */
endmodule

Asyn_Fifo/py_tb/dump.vcd
$version Generated by VerilatedVcd $end
$timescale 1ps $end
 $scope module  $end
  $var wire 1 # w_rst $end
  $var wire 1 $ w_en $end
  $var wire 1 % r_rst $end
  $var wire 1 & r_en $end
  $var wire 8 ' w_data [7:0] $end
  $var wire 8 ( r_data [7:0] $end
  $var wire 1 ) w_full $end
  $var wire 1 * r_empty $end
  $scope module simple_demo_tb $end
   $var wire 1 + w_rst $end
   $var wire 1 , w_en $end
   $var wire 1 - r_rst $end
   $var wire 1 . r_en $end
   $var wire 8 / w_data [7:0] $end
   $var wire 8 0 r_data [7:0] $end
   $var wire 1 1 w_full $end
   $var wire 1 2 r_empty $end
   $var wire 1 3 w_clk $end
   $var wire 1 4 r_clk $end
   $var wire 32 } DATA_SIZE [31:0] $end
   $var wire 32 ~ ADDR_SIZE [31:0] $end
   $scope module dut $end
    $var wire 32 } DATA_SIZE [31:0] $end
    $var wire 32 ~ ADDR_SIZE [31:0] $end
    $var wire 8 5 r_data [7:0] $end
    $var wire 1 6 w_full $end
    $var wire 1 7 r_empty $end
    $var wire 8 8 w_data [7:0] $end
    $var wire 1 9 w_en $end
    $var wire 1 : w_rst $end
    $var wire 1 ; w_clk $end
    $var wire 1 < r_en $end
    $var wire 1 = r_clk $end
    $var wire 1 > r_rst $end
    $var wire 4 ? w_addr [3:0] $end
    $var wire 4 @ r_addr [3:0] $end
    $var wire 5 A w_ptr_i [4:0] $end
    $var wire 5 B r_ptr_i [4:0] $end
    $var wire 5 C w_ptr_o [4:0] $end
    $var wire 5 D r_ptr_o [4:0] $end
    $scope module fifo_mem $end
     $var wire 32 ~ ADDR_SIZE [31:0] $end
     $var wire 32 } DATA_SIZE [31:0] $end
     $var wire 8 E r_data [7:0] $end
     $var wire 4 F r_addr [3:0] $end
     $var wire 8 G w_data [7:0] $end
     $var wire 1 H w_en $end
     $var wire 1 I w_clk $end
     $var wire 1 J w_full $end
     $var wire 4 K w_addr [3:0] $end
     $var wire 32 !! DEPTH [31:0] $end
     $var wire 8 L fifo_data[0] [7:0] $end
     $var wire 8 M fifo_data[1] [7:0] $end
     $var wire 8 N fifo_data[2] [7:0] $end
     $var wire 8 O fifo_data[3] [7:0] $end
     $var wire 8 P fifo_data[4] [7:0] $end
     $var wire 8 Q fifo_data[5] [7:0] $end
     $var wire 8 R fifo_data[6] [7:0] $end
     $var wire 8 S fifo_data[7] [7:0] $end
     $var wire 8 T fifo_data[8] [7:0] $end
     $var wire 8 U fifo_data[9] [7:0] $end
     $var wire 8 V fifo_data[10] [7:0] $end
     $var wire 8 W fifo_data[11] [7:0] $end
     $var wire 8 X fifo_data[12] [7:0] $end
     $var wire 8 Y fifo_data[13] [7:0] $end
     $var wire 8 Z fifo_data[14] [7:0] $end
     $var wire 8 [ fifo_data[15] [7:0] $end
    $upscope $end
    $scope module r_empty_checker $end
     $var wire 32 ~ ADDR_SIZE [31:0] $end
     $var wire 1 \ r_empty $end
     $var wire 5 ] r_ptr_gray [4:0] $end
     $var wire 4 ^ r_addr [3:0] $end
     $var wire 5 _ w_ptr_gray [4:0] $end
     $var wire 1 ` r_en $end
     $var wire 1 a r_clk $end
     $var wire 1 b r_rst $end
     $var wire 5 c r_ptr_gray_next [4:0] $end
     $var wire 5 d r_ptr_bin [4:0] $end
     $var wire 5 e r_ptr_bin_next [4:0] $end
     $var wire 1 f r_empty_tmp $end
    $upscope $end
    $scope module r_sync $end
     $var wire 32 ~ ADDR_SIZE [31:0] $end
     $var wire 5 g i_ptr [4:0] $end
     $var wire 5 h o_ptr [4:0] $end
     $var wire 1 i clk $end
     $var wire 1 j rst $end
     $var wire 5 k ptr_temp [4:0] $end
    $upscope $end
    $scope module w_full_checker $end
     $var wire 32 ~ ADDR_SIZE [31:0] $end
     $var wire 5 l r_ptr_gray [4:0] $end
     $var wire 1 m w_clk $end
     $var wire 1 n w_rst $end
     $var wire 1 o w_en $end
     $var wire 4 p w_addr [3:0] $end
     $var wire 1 q w_full $end
     $var wire 5 r w_ptr_gray [4:0] $end
     $var wire 5 s w_ptr_gray_next [4:0] $end
     $var wire 5 t r_ptr_gray_next [4:0] $end
     $var wire 1 u w_full_tmp $end
     $var wire 5 v w_ptr_bin [4:0] $end
     $var wire 5 w w_ptr_bin_next [4:0] $end
    $upscope $end
    $scope module w_sync $end
     $var wire 32 ~ ADDR_SIZE [31:0] $end
     $var wire 5 x i_ptr [4:0] $end
     $var wire 5 y o_ptr [4:0] $end
     $var wire 1 z clk $end
     $var wire 1 { rst $end
     $var wire 5 | ptr_temp [4:0] $end
    $upscope $end
   $upscope $end
  $upscope $end
 $upscope $end
$enddefinitions $end


#0
0#
0$
0%
0&
b00000000 '
b00000000 (
0)
0*
0+
0,
0-
0.
b00000000 /
b00000000 0
01
02
03
04
b00000000 5
06
07
b00000000 8
09
0:
0;
0<
0=
0>
b0000 ?
b0000 @
b00000 A
b00000 B
b00000 C
b00000 D
b00000000 E
b0000 F
b00000000 G
0H
0I
0J
b0000 K
b00000000 L
b00000000 M
b00000000 N
b00000000 O
b00000000 P
b00000000 Q
b00000000 R
b00000000 S
b00000000 T
b00000000 U
b00000000 V
b00000000 W
b00000000 X
b00000000 Y
b00000000 Z
b00000000 [
0\
b00000 ]
b0000 ^
b00000 _
0`
0a
0b
b00000 c
b00000 d
b00000 e
1f
b00000 g
b00000 h
0i
0j
b00000 k
b00000 l
0m
0n
0o
b0000 p
0q
b00000 r
b00000 s
b11000 t
0u
b00000 v
b00000 w
b00000 x
b00000 y
0z
0{
b00000 |
b00000000000000000000000000001000 }
b00000000000000000000000000000100 ~
b00000000000000000000000000010000 !!
#5000
13
1;
1I
1m
1z
#7000
1*
12
14
17
1=
1\
1a
1i
#10000
03
0;
0I
0m
0z
#14000
04
0=
0a
0i
#15000
13
1;
1I
1m
1z
#20000
03
0;
0I
0m
0z
#21000
14
1=
1a
1i
#25000
13
1;
1I
1m
1z
#28000
1%
1-
04
0=
1>
0a
1b
0i
1j
#30000
03
0;
0I
0m
0z
#35000
13
14
1;
1=
1I
1a
1i
1m
1z
#40000
03
0;
0I
0m
0z
#42000
04
0=
0a
0i
#45000
13
1;
1I
1m
1z
#49000
14
1=
1a
1i
#50000
03
0;
0I
0m
0z
#55000
13
1;
1I
1m
1z
#56000
04
0=
0a
0i
#60000
1#
1+
03
1:
0;
0I
0m
1n
0z
1{
#63000
14
1=
1a
1i
#65000
13
1;
1I
1m
1z
#70000
03
04
0;
0=
0I
0a
0i
0m
0z
#75000
13
1;
1I
1m
1z
#77000
14
1=
1a
1i
#80000
03
0;
0I
0m
0z
#84000
04
0=
0a
0i
#85000
13
1;
1I
1m
1z
#90000
03
0;
0I
0m
0z
#91000
14
1=
1a
1i
#95000
1$
b01111101 '
b01111101 (
1,
b01111101 /
b01111101 0
13
b01111101 5
b01111101 8
19
1;
b01111101 E
b01111101 G
1H
1I
b01111101 L
1m
1o
b00001 s
b00001 w
1z
#98000
04
0=
0a
0i
#100000
03
0;
0I
0m
0z
#105000
0$
0,
13
14
09
1;
1=
b0001 ?
b00001 A
0H
1I
b0001 K
b01111101 M
1a
1i
1m
0o
b0001 p
b00001 r
b00001 v
b00001 x
1z
#110000
03
0;
0I
0m
0z
#112000
04
0=
0a
0i
#115000
1$
b10010101 '
1,
b10010101 /
13
b10010101 8
19
1;
b10010101 G
1H
1I
b10010101 M
1m
1o
b00011 s
b00010 w
1z
b00001 |
#119000
14
1=
1a
1i
#120000
03
0;
0I
0m
0z
#125000
b11101010 '
b11101010 /
13
b11101010 8
1;
b0010 ?
b00011 A
b00001 C
b11101010 G
1I
b0010 K
b11101010 N
b00001 _
0f
1m
b0010 p
b00011 r
b00010 s
b00010 v
b00011 w
b00011 x
b00001 y
1z
#126000
04
0=
0a
0i
#130000
03
0;
0I
0m
0z
#133000
1&
0*
1.
02
14
07
1<
1=
0\
1`
1a
b00001 c
b00001 e
1f
1i
#135000
b11010111 '
b11010111 /
13
b11010111 8
1;
b0011 ?
b00010 A
b11010111 G
1I
b0011 K
b11010111 O
1m
b0011 p
b00010 r
b00110 s
b00011 v
b00100 w
b00010 x
1z
b00011 |
#140000
03
04
0;
0=
0I
0a
0i
0m
0z
#145000
b10100000 '
b10100000 /
13
b10100000 8
1;
b0100 ?
b00110 A
b00011 C
b10100000 G
1I
b0100 K
b10100000 P
b00011 _
0f
1m
b0100 p
b00110 r
b00111 s
b00100 v
b00101 w
b00110 x
b00011 y
1z
b00010 |
#147000
0&
b10010101 (
0.
b10010101 0
14
b10010101 5
0<
1=
b0001 @
b00001 B
b10010101 E
b0001 F
b00001 ]
b0001 ^
0`
1a
b00001 d
b00001 g
1i
#150000
03
0;
0I
0m
0z
#154000
04
0=
0a
0i
#155000
0$
0,
13
09
1;
b0101 ?
b00111 A
b00010 C
0H
1I
b0101 K
b10100000 Q
b00010 _
1m
0o
b0101 p
b00111 r
b00101 v
b00111 x
b00010 y
1z
b00110 |
#160000
03
0;
0I
0m
0z
#161000
14
1=
1a
1i
b00001 k
#165000
1$
b10111011 '
1,
b10111011 /
13
b10111011 8
19
1;
b00110 C
b10111011 G
1H
1I
b10111011 Q
b00110 _
1m
1o
b00101 s
b00110 w
b00110 y
1z
b00111 |
#168000
04
0=
0a
0i
#170000
03
0;
0I
0m
0z
#175000
0$
1&
0,
1.
13
14
09
1;
1<
1=
b0110 ?
b00101 A
b00111 C
b00001 D
0H
1I
b0110 K
b10111011 R
b00111 _
1`
1a
b00011 c
b00010 e
b00001 h
1i
b00001 l
1m
0o
b0110 p
b00101 r
b11001 t
b00110 v
b00101 x
b00111 y
1z
#180000
03
0;
0I
0m
0z
#182000
04
0=
0a
0i
#185000
1$
b10011111 '
1,
b10011111 /
13
b10011111 8
19
1;
b10011111 G
1H
1I
b10011111 R
1m
1o
b00100 s
b00111 w
1z
b00101 |
#189000
0&
b11101010 (
0.
b11101010 0
14
b11101010 5
0<
1=
b0010 @
b00011 B
b11101010 E
b0010 F
b00011 ]
b0010 ^
0`
1a
b00010 d
b00011 g
1i
#190000
03
0;
0I
0m
0z
#195000
b00011000 '
b00011000 /
13
b00011000 8
1;
b0111 ?
b00100 A
b00101 C
b00011000 G
1I
b0111 K
b00011000 S
b00101 _
1m
b0111 p
b00100 r
b01100 s
b00111 v
b01000 w
b00100 x
b00101 y
1z
#196000
04
0=
0a
0i
#200000
03
0;
0I
0m
0z
#203000
14
1=
1a
1i
b00011 k
#205000
b00010100 '
b00010100 /
13
b00010100 8
1;
b1000 ?
b01100 A
b00010100 G
1I
b1000 K
b00010100 T
1m
b1000 p
b01100 r
b01101 s
b01000 v
b01001 w
b01100 x
1z
b00100 |
#210000
03
04
0;
0=
0I
0a
0i
0m
0z
#215000
b10000101 '
b10000101 /
13
b10000101 8
1;
b1001 ?
b01101 A
b00100 C
b10000101 G
1I
b1001 K
b10000101 U
b00100 _
1m
b1001 p
b01101 r
b01111 s
b01001 v
b01010 w
b01101 x
b00100 y
1z
b01100 |
#217000
14
1=
b00011 D
1a
b00011 h
1i
b00011 l
b11011 t
#220000
03
0;
0I
0m
0z
#224000
04
0=
0a
0i
#225000
b01111101 '
b01111101 /
13
b01111101 8
1;
b1010 ?
b01111 A
b01100 C
b01111101 G
1I
b1010 K
b01111101 V
b01100 _
1m
b1010 p
b01111 r
b01110 s
b01010 v
b01011 w
b01111 x
b01100 y
1z
b01101 |
#230000
03
0;
0I
0m
0z
#231000
14
1=
1a
1i
#235000
b00110100 '
b00110100 /
13
b00110100 8
1;
b1011 ?
b01110 A
b01101 C
b00110100 G
1I
b1011 K
b00110100 W
b01101 _
1m
b1011 p
b01110 r
b01010 s
b01011 v
b01100 w
b01110 x
b01101 y
1z
b01111 |
#238000
04
0=
0a
0i
#240000
03
0;
0I
0m
0z
#245000
1&
b00000100 '
1.
b00000100 /
13
14
b00000100 8
1;
1<
1=
b1100 ?
b01010 A
b01111 C
b00000100 G
1I
b1100 K
b00000100 X
b01111 _
1`
1a
b00010 c
b00011 e
1i
1m
b1100 p
b01010 r
b01011 s
b01100 v
b01101 w
b01010 x
b01111 y
1z
b01110 |
#250000
03
0;
0I
0m
0z
#252000
04
0=
0a
0i
#255000
0$
0,
13
09
1;
b1101 ?
b01011 A
b01110 C
0H
1I
b1101 K
b00000100 Y
b01110 _
1m
0o
b1101 p
b01011 r
b01101 v
b01011 x
b01110 y
1z
b01010 |
#259000
0&
b11010111 (
0.
b11010111 0
14
b11010111 5
0<
1=
b0011 @
b00010 B
b11010111 E
b0011 F
b00010 ]
b0011 ^
0`
1a
b00011 d
b00010 g
1i
#260000
03
0;
0I
0m
0z
#265000
1$
b00001010 '
1,
b00001010 /
13
b00001010 8
19
1;
b01010 C
b00001010 G
1H
1I
b00001010 Y
b01010 _
1m
1o
b01001 s
b01110 w
b01010 y
1z
b01011 |
#266000
04
0=
0a
0i
#270000
03
0;
0I
0m
0z
#273000
1&
1.
14
1<
1=
1`
1a
b00110 c
b00100 e
1i
b00010 k
#275000
b10110000 '
b10110000 /
13
b10110000 8
1;
b1110 ?
b01001 A
b01011 C
b10110000 G
1I
b1110 K
b10110000 Z
b01011 _
1m
b1110 p
b01001 r
b01000 s
b01110 v
b01111 w
b01001 x
b01011 y
1z
#280000
03
04
0;
0=
0I
0a
0i
0m
0z
#285000
b00001100 '
b00001100 /
13
b00001100 8
1;
b1111 ?
b01000 A
b00001100 G
1I
b1111 K
b00001100 [
1m
b1111 p
b01000 r
b11000 s
b01111 v
b10000 w
b01000 x
1z
b01001 |
#287000
0&
b10100000 (
0.
b10100000 0
14
b10100000 5
0<
1=
b0100 @
b00110 B
b00010 D
b10100000 E
b0100 F
b00110 ]
b0100 ^
0`
1a
b00100 d
b00110 g
b00010 h
1i
b00010 l
b11010 t
#290000
03
0;
0I
0m
0z
#294000
04
0=
0a
0i
#295000
b01011110 '
b01011110 /
13
b01011110 8
1;
b0000 ?
b11000 A
b01001 C
b01011110 G
1I
b0000 K
b01011110 L
b01001 _
1m
b0000 p
b11000 r
b11001 s
b10000 v
b10001 w
b11000 x
b01001 y
1z
b01000 |
#300000
03
0;
0I
0m
0z
#301000
14
1=
1a
1i
b00110 k
#305000
b00110110 '
b00110110 /
13
b00110110 8
1;
b0001 ?
b11001 A
b01000 C
b00110110 G
1I
b0001 K
b00110110 M
b01000 _
1m
b0001 p
b11001 r
b11011 s
b10001 v
b10010 w
b11001 x
b01000 y
1z
b11000 |
#308000
04
0=
0a
0i
#310000
03
0;
0I
0m
0z
#315000
1&
b00001100 '
1.
b00001100 /
13
14
b00001100 8
1;
1<
1=
b0010 ?
b11011 A
b11000 C
b00110 D
b00001100 G
1I
b0010 K
b00001100 N
b11000 _
1`
1a
b00111 c
b00101 e
b00110 h
1i
b00110 l
1m
b0010 p
b11011 r
b11010 s
b11110 t
b10010 v
b10011 w
b11011 x
b11000 y
1z
b11001 |
#320000
03
0;
0I
0m
0z
#322000
04
0=
0a
0i
#325000
b01011010 '
b01011010 /
13
b01011010 8
1;
b0011 ?
b11010 A
b11001 C
b01011010 G
1I
b0011 K
b01011010 O
b11001 _
1m
b0011 p
b11010 r
b11110 s
1u
b10011 v
b10100 w
b11010 x
b11001 y
1z
b11011 |
#329000
0&
b10111011 (
0.
b10111011 0
14
b10111011 5
0<
1=
b0101 @
b00111 B
b10111011 E
b0101 F
b00111 ]
b0101 ^
0`
1a
b00101 d
b00111 g
1i
#330000
03
0;
0I
0m
0z
#335000
0$
b00000000 '
1)
0,
b00000000 /
11
13
16
b00000000 8
09
1;
b0100 ?
b11110 A
b11011 C
b00000000 G
0H
1I
1J
b0100 K
b11011 _
1m
0o
b0100 p
1q
b11110 r
b10100 v
b11110 x
b11011 y
1z
b11010 |
#336000
04
0=
0a
0i
#340000
03
0;
0I
0m
0z
#343000
14
1=
1a
1i
b00111 k
#345000
13
1;
b11010 C
1I
b11010 _
1m
b11010 y
1z
b11110 |
#350000
03
04
0;
0=
0I
0a
0i
0m
0z
#355000
13
1;
b11110 C
1I
b11110 _
1m
b11110 y
1z
#357000
14
1=
b00111 D
1a
b00111 h
1i
b00111 l
b11111 t
0u
#360000
03
0;
0I
0m
0z
#364000
04
0=
0a
0i
#365000
1$
b01101010 '
0)
1,
b01101010 /
01
13
06
b01101010 8
19
1;
b01101010 G
1H
1I
0J
b01101010 P
1m
1o
0q
b11111 s
1u
b10101 w
1z
#370000
03
0;
0I
0m
0z
#371000
1&
1.
14
1<
1=
1`
1a
b00101 c
b00110 e
1i
#375000
0$
b00000000 '
1)
0,
b00000000 /
11
13
16
b00000000 8
09
1;
b0101 ?
b11111 A
b00000000 G
0H
1I
1J
b0101 K
1m
0o
b0101 p
1q
b11111 r
b10101 v
b11111 x
1z
#378000
04
0=
0a
0i
#380000
03
0;
0I
0m
0z
#385000
0&
b10011111 (
0.
b10011111 0
13
14
b10011111 5
1;
0<
1=
b0110 @
b00101 B
b10011111 E
b0110 F
1I
b00101 ]
b0110 ^
0`
1a
b00110 d
b00101 g
1i
1m
1z
b11111 |
#390000
03
0;
0I
0m
0z
#392000
04
0=
0a
0i
#395000
13
1;
b11111 C
1I
b11111 _
1m
b11111 y
1z
#399000
14
1=
1a
1i
b00101 k
#400000
03
0;
0I
0m
0z
#405000
13
1;
1I
1m
1z
#406000
04
0=
0a
0i
#410000
03
0;
0I
0m
0z
#413000
1&
1.
14
1<
1=
b00101 D
1`
1a
b00100 c
b00111 e
b00101 h
1i
b00101 l
b11101 t
0u
#415000
1$
b11000111 '
0)
1,
b11000111 /
01
13
06
b11000111 8
19
1;
b11000111 G
1H
1I
0J
b11000111 Q
1m
1o
0q
b11101 s
1u
b10110 w
1z
#420000
03
04
0;
0=
0I
0a
0i
0m
0z
#425000
0$
b00000000 '
1)
0,
b00000000 /
11
13
16
b00000000 8
09
1;
b0110 ?
b11101 A
b00000000 G
0H
1I
1J
b0110 K
1m
0o
b0110 p
1q
b11101 r
b10110 v
b11101 x
1z
#427000
0&
b00011000 (
0.
b00011000 0
14
b00011000 5
0<
1=
b0111 @
b00100 B
b00011000 E
b0111 F
b00100 ]
b0111 ^
0`
1a
b00111 d
b00100 g
1i
#430000
03
0;
0I
0m
0z
#434000
04
0=
0a
0i
#435000
13
1;
1I
1m
1z
b11101 |
#440000
03
0;
0I
0m
0z
#441000
1&
1.
14
1<
1=
1`
1a
b01100 c
b01000 e
1i
b00100 k
#445000
13
1;
b11101 C
1I
b11101 _
1m
b11101 y
1z
#448000
04
0=
0a
0i
#450000
03
0;
0I
0m
0z
#455000
0&
b00010100 (
0.
b00010100 0
13
14
b00010100 5
1;
0<
1=
b1000 @
b01100 B
b00100 D
b00010100 E
b1000 F
1I
b01100 ]
b1000 ^
0`
1a
b01000 d
b01100 g
b00100 h
1i
b00100 l
1m
b11100 t
0u
1z
#460000
03
0;
0I
0m
0z
#462000
04
0=
0a
0i
#465000
1$
b10100010 '
0)
1,
b10100010 /
01
13
06
b10100010 8
19
1;
b10100010 G
1H
1I
0J
b10100010 R
1m
1o
0q
b11100 s
1u
b10111 w
1z
#469000
14
1=
1a
1i
b01100 k
#470000
03
0;
0I
0m
0z
#475000
0$
b00000000 '
1)
0,
b00000000 /
11
13
16
b00000000 8
09
1;
b0111 ?
b11100 A
b00000000 G
0H
1I
1J
b0111 K
1m
0o
b0111 p
1q
b11100 r
b10111 v
b11100 x
1z
#476000
04
0=
0a
0i
#480000
03
0;
0I
0m
0z
#483000
14
1=
b01100 D
1a
b01100 h
1i
b01100 l
b10100 t
0u
#485000
1$
b11110001 '
0)
1,
b11110001 /
01
13
06
b11110001 8
19
1;
b11110001 G
1H
1I
0J
b11110001 S
1m
1o
0q
b10100 s
1u
b11000 w
1z
b11100 |
#490000
03
04
0;
0=
0I
0a
0i
0m
0z
#495000
0$
1)
0,
11
13
16
09
1;
b1000 ?
b10100 A
b11100 C
0H
1I
1J
b1000 K
b11100 _
1m
0o
b1000 p
1q
b10100 r
b11000 v
b10100 x
b11100 y
1z
#497000
1&
1.
14
1<
1=
1`
1a
b01101 c
b01001 e
1i
#500000
03
0;
0I
0m
0z
#504000
04
0=
0a
0i
#505000
b00000000 '
b00000000 /
13
b00000000 8
1;
b00000000 G
1I
1m
1z
b10100 |
#510000
03
0;
0I
0m
0z
#511000
0&
b10000101 (
0.
b10000101 0
14
b10000101 5
0<
1=
b1001 @
b01101 B
b10000101 E
b1001 F
b01101 ]
b1001 ^
0`
1a
b01001 d
b01101 g
1i
#515000
13
1;
b10100 C
1I
b10100 _
1m
b10100 y
1z
#518000
04
0=
0a
0i
#520000
03
0;
0I
0m
0z
#525000
13
14
1;
1=
1I
1a
1i
b01101 k
1m
1z
#530000
03
0;
0I
0m
0z
#532000
04
0=
0a
0i
#535000
13
1;
1I
1m
1z
